<?xml version='1.0' encoding='UTF-8'?><ResultsList path="SimpleSample_Desktop_2012/DirectXTK_Desktop_2012/Src/EffectCommon.h"><VersionInfos><StorageInfo ownerId="com.parasoft.xtest.checkers.api.execution" resultId="IExecutionViolation" ver="2" /><StorageInfo ownerId="com.parasoft.xtest.checkers.api.execution" resultId="InsureViolation" ver="3" /><StorageInfo ownerId="com.parasoft.xtest.checkers.api.codereview" resultId="ICodeReviewViolation" ver="2" /><StorageInfo ownerId="com.parasoft.xtest.checkers.api.codereview" resultId="ICodeReviewUndefinedAuthorsInfo" ver="1" /><StorageInfo ownerId="com.parasoft.xtest.checkers.api.codereview" resultId="ICodeReviewUnmatchedPathInfo" ver="1" /><StorageInfo ownerId="com.parasoft.xtest.checkers.api.codereview" resultId="ICodeReviewScannerInfo" ver="2" /><StorageInfo ownerId="com.parasoft.xtest.checkers.api.generation" resultId="IGenerationInfo" ver="2" /><StorageInfo ownerId="com.parasoft.xtest.checkers.api.generation" resultId="IGenerationProjectInfo" ver="2" /><StorageInfo ownerId="com.parasoft.xtest.checkers.api.scope" resultId="IScopeProjectInfo" ver="3" /><StorageInfo ownerId="com.parasoft.xtest.checkers.api.standards" resultId="IMetricsViolation" ver="2" /><StorageInfo ownerId="com.parasoft.xtest.checkers.api.standards" resultId="IFlowAnalysisViolation" ver="2" /><StorageInfo ownerId="com.parasoft.xtest.checkers.api.standards" resultId="ICodingStandardsViolation" ver="2" /><StorageInfo ownerId="com.parasoft.xtest.checkers.api.standards" resultId="IMetricEstimationInfo" ver="2" /><StorageInfo ownerId="com.parasoft.xtest.checkers.api.standards" resultId="IDupCodeViolation" ver="2" /></VersionInfos><ResultInfo resultId="ICodingStandardsViolation" ownerId="com.parasoft.xtest.checkers.api.standards" violKeys="null;null;null;null;null;null;null;null;null;null;null;null;null;null;null;null;null;null;null;null;null;null;null;null;null;null;null;null;null"><StdViol sev="4" ln="219" cat="STL-37" hash="-526459925" tool="c++test" locType="sr" msg="Use vector or string instead of array: VertexShaderIndices" lang="cpp" rule="STL-37-DOWNGRADED" config="1" auth="464642" locStartln="219" locStartPos="25" locEndLn="219" locEndPos="26" locFile="SimpleSample_Desktop_2012/DirectXTK_Desktop_2012/Src/EffectCommon.h" /><StdViol sev="4" ln="216" cat="STL-37" hash="-526459925" tool="c++test" locType="sr" msg="Use vector or string instead of array: VertexShaderBytecode" lang="cpp" rule="STL-37-DOWNGRADED" config="1" auth="464642" locStartln="216" locStartPos="36" locEndLn="216" locEndPos="37" locFile="SimpleSample_Desktop_2012/DirectXTK_Desktop_2012/Src/EffectCommon.h" /><StdViol sev="3" ln="117" cat="MRM" hash="-526459925" tool="c++test" locType="sr" msg="Class 'ShaderBytecode' shall declare a copy assignment operator" lang="cpp" rule="MRM-49" config="1" auth="464642" locStartln="117" locStartPos="11" locEndLn="117" locEndPos="12" locFile="SimpleSample_Desktop_2012/DirectXTK_Desktop_2012/Src/EffectCommon.h" /><StdViol sev="3" ln="70" cat="OPT" hash="-526459925" tool="c++test" locType="sr" msg="The parameter 'worldView' of function 'SetConstants' is passed by value" lang="cpp" rule="OPT-14" config="1" auth="464642" locStartln="70" locStartPos="70" locEndLn="70" locEndPos="71" locFile="SimpleSample_Desktop_2012/DirectXTK_Desktop_2012/Src/EffectCommon.h" /><StdViol sev="2" ln="164" cat="OOP" hash="-526459925" tool="c++test" locType="sr" msg="Data members 'fog' is declared as 'public'" lang="cpp" rule="OOP-18" config="1" auth="464642" locStartln="164" locStartPos="18" locEndLn="164" locEndPos="19" locFile="SimpleSample_Desktop_2012/DirectXTK_Desktop_2012/Src/EffectCommon.h" /><StdViol sev="1" ln="230" cat="CODSTA-CPP" hash="-526459925" tool="c++test" locType="sr" msg="Constructor 'DeviceResources' allowing conversion should be made explicit" lang="cpp" rule="CODSTA-CPP-04" config="1" auth="464642" locStartln="230" locStartPos="12" locEndLn="230" locEndPos="13" locFile="SimpleSample_Desktop_2012/DirectXTK_Desktop_2012/Src/EffectCommon.h" /><StdViol sev="2" ln="161" cat="OOP" hash="-526459925" tool="c++test" locType="sr" msg="Data members 'constants' is declared as 'public'" lang="cpp" rule="OOP-18" config="1" auth="464642" locStartln="161" locStartPos="44" locEndLn="161" locEndPos="45" locFile="SimpleSample_Desktop_2012/DirectXTK_Desktop_2012/Src/EffectCommon.h" /><StdViol sev="2" ln="166" cat="OOP" hash="-526459925" tool="c++test" locType="sr" msg="Data members 'texture' is declared as 'public'" lang="cpp" rule="OOP-18" config="1" auth="464642" locStartln="166" locStartPos="57" locEndLn="166" locEndPos="58" locFile="SimpleSample_Desktop_2012/DirectXTK_Desktop_2012/Src/EffectCommon.h" /><StdViol sev="3" ln="129" cat="CODSTA-CPP" hash="-526459925" tool="c++test" locType="sr" msg="Declare parameter 'device' as const" lang="cpp" rule="CODSTA-CPP-53" config="1" auth="464642" locStartln="129" locStartPos="46" locEndLn="129" locEndPos="47" locFile="SimpleSample_Desktop_2012/DirectXTK_Desktop_2012/Src/EffectCommon.h" /><StdViol sev="4" ln="99" cat="STL-37" hash="-526459925" tool="c++test" locType="sr" msg="Use vector or string instead of array: lightDiffuseColor" lang="cpp" rule="STL-37-DOWNGRADED" config="1" auth="464642" locStartln="99" locStartPos="17" locEndLn="99" locEndPos="18" locFile="SimpleSample_Desktop_2012/DirectXTK_Desktop_2012/Src/EffectCommon.h" /><StdViol sev="2" ln="139" cat="OOP" hash="-526459925" tool="c++test" locType="sr" msg="Data members 'mDefaultTexture' is declared as 'protected'" lang="cpp" rule="OOP-19" config="1" auth="464642" locStartln="139" locStartPos="57" locEndLn="139" locEndPos="58" locFile="SimpleSample_Desktop_2012/DirectXTK_Desktop_2012/Src/EffectCommon.h" /><StdViol sev="1" ln="129" cat="CODSTA-CPP" hash="-526459925" tool="c++test" locType="sr" msg="Constructor 'EffectDeviceResources' allowing conversion should be made explicit" lang="cpp" rule="CODSTA-CPP-04" config="1" auth="464642" locStartln="129" locStartPos="8" locEndLn="129" locEndPos="9" locFile="SimpleSample_Desktop_2012/DirectXTK_Desktop_2012/Src/EffectCommon.h" /><StdViol sev="4" ln="258" cat="STL-37" hash="-526459925" tool="c++test" locType="sr" msg="Use vector or string instead of array: mVertexShaders" lang="cpp" rule="STL-37-DOWNGRADED" config="1" auth="464642" locStartln="258" locStartPos="55" locEndLn="258" locEndPos="56" locFile="SimpleSample_Desktop_2012/DirectXTK_Desktop_2012/Src/EffectCommon.h" /><StdViol sev="3" ln="87" cat="OOP" hash="-526459925" tool="c++test" locType="sr" msg="Hidden function in DirectX::EffectLights class: DirectX::EffectColor::SetConstants(int &amp;, __m128 &amp;)" lang="cpp" rule="OOP-53" config="1" auth="464642" locStartln="87" locStartPos="11" locEndLn="87" locEndPos="12" locFile="SimpleSample_Desktop_2012/DirectXTK_Desktop_2012/Src/EffectCommon.h" /><StdViol sev="5" ln="147" cat="OPT-13" hash="-526459925" tool="c++test" locType="sr" msg="Members 'mConstantBuffer, mDeviceResources' of class 'EffectBase' are declared in suboptimal order for memory layout" lang="cpp" rule="OPT-13-DOWNGRADED" config="1" auth="464642" locStartln="147" locStartPos="10" locEndLn="147" locEndPos="11" locFile="SimpleSample_Desktop_2012/DirectXTK_Desktop_2012/Src/EffectCommon.h" /><StdViol sev="4" ln="98" cat="STL-37" hash="-526459925" tool="c++test" locType="sr" msg="Use vector or string instead of array: lightEnabled" lang="cpp" rule="STL-37-DOWNGRADED" config="1" auth="464642" locStartln="98" locStartPos="13" locEndLn="98" locEndPos="14" locFile="SimpleSample_Desktop_2012/DirectXTK_Desktop_2012/Src/EffectCommon.h" /><StdViol sev="2" ln="163" cat="OOP" hash="-526459925" tool="c++test" locType="sr" msg="Data members 'matrices' is declared as 'public'" lang="cpp" rule="OOP-18" config="1" auth="464642" locStartln="163" locStartPos="23" locEndLn="163" locEndPos="24" locFile="SimpleSample_Desktop_2012/DirectXTK_Desktop_2012/Src/EffectCommon.h" /><StdViol sev="2" ln="138" cat="OOP" hash="-526459925" tool="c++test" locType="sr" msg="Data members 'mDevice' is declared as 'protected'" lang="cpp" rule="OOP-19" config="1" auth="464642" locStartln="138" locStartPos="45" locEndLn="138" locEndPos="46" locFile="SimpleSample_Desktop_2012/DirectXTK_Desktop_2012/Src/EffectCommon.h" /><StdViol sev="1" ln="151" cat="CODSTA-CPP" hash="-526459925" tool="c++test" locType="sr" msg="Constructor 'EffectBase' allowing conversion should be made explicit" lang="cpp" rule="CODSTA-CPP-04" config="1" auth="464642" locStartln="151" locStartPos="8" locEndLn="151" locEndPos="9" locFile="SimpleSample_Desktop_2012/DirectXTK_Desktop_2012/Src/EffectCommon.h" /><StdViol sev="4" ln="217" cat="STL-37" hash="-526459925" tool="c++test" locType="sr" msg="Use vector or string instead of array: PixelShaderBytecode" lang="cpp" rule="STL-37-DOWNGRADED" config="1" auth="464642" locStartln="217" locStartPos="36" locEndLn="217" locEndPos="37" locFile="SimpleSample_Desktop_2012/DirectXTK_Desktop_2012/Src/EffectCommon.h" /><StdViol sev="4" ln="220" cat="STL-37" hash="-526459925" tool="c++test" locType="sr" msg="Use vector or string instead of array: PixelShaderIndices" lang="cpp" rule="STL-37-DOWNGRADED" config="1" auth="464642" locStartln="220" locStartPos="25" locEndLn="220" locEndPos="26" locFile="SimpleSample_Desktop_2012/DirectXTK_Desktop_2012/Src/EffectCommon.h" /><StdViol sev="5" ln="227" cat="OOP" hash="-526459925" tool="c++test" locType="sr" msg="Do not overuse inheritance" lang="cpp" rule="OOP-37" config="1" auth="464642" locStartln="227" locStartPos="14" locEndLn="227" locEndPos="15" locFile="SimpleSample_Desktop_2012/DirectXTK_Desktop_2012/Src/EffectCommon.h" /><StdViol sev="3" ln="254" cat="OOP" hash="-526459925" tool="c++test" locType="sr" msg="The function 'GetDefaultTexture' redefines functions from following base classes: EffectDeviceResources" lang="cpp" rule="OOP-32" config="1" auth="464642" locStartln="254" locStartPos="38" locEndLn="254" locEndPos="39" locFile="SimpleSample_Desktop_2012/DirectXTK_Desktop_2012/Src/EffectCommon.h" /><StdViol sev="4" ln="259" cat="STL-37" hash="-526459925" tool="c++test" locType="sr" msg="Use vector or string instead of array: mPixelShaders" lang="cpp" rule="STL-37-DOWNGRADED" config="1" auth="464642" locStartln="259" locStartPos="54" locEndLn="259" locEndPos="55" locFile="SimpleSample_Desktop_2012/DirectXTK_Desktop_2012/Src/EffectCommon.h" /><StdViol sev="3" ln="117" cat="MRM" hash="-526459925" tool="c++test" locType="sr" msg="Class 'ShaderBytecode' shall declare a copy constructor" lang="cpp" rule="MRM-49" config="1" auth="464642" locStartln="117" locStartPos="11" locEndLn="117" locEndPos="12" locFile="SimpleSample_Desktop_2012/DirectXTK_Desktop_2012/Src/EffectCommon.h" /><StdViol sev="2" ln="168" cat="OOP" hash="-526459925" tool="c++test" locType="sr" msg="Data members 'dirtyFlags' is declared as 'public'" lang="cpp" rule="OOP-18" config="1" auth="464642" locStartln="168" locStartPos="12" locEndLn="168" locEndPos="13" locFile="SimpleSample_Desktop_2012/DirectXTK_Desktop_2012/Src/EffectCommon.h" /><StdViol sev="3" ln="129" cat="MISRA2004" hash="-526459925" tool="c++test" locType="sr" msg="Pass parameter &quot;device&quot; with const specifier" lang="cpp" rule="MISRA2004-16_7" config="1" auth="464642" locStartln="129" locStartPos="46" locEndLn="129" locEndPos="47" locFile="SimpleSample_Desktop_2012/DirectXTK_Desktop_2012/Src/EffectCommon.h" /><StdViol sev="4" ln="100" cat="STL-37" hash="-526459925" tool="c++test" locType="sr" msg="Use vector or string instead of array: lightSpecularColor" lang="cpp" rule="STL-37-DOWNGRADED" config="1" auth="464642" locStartln="100" locStartPos="17" locEndLn="100" locEndPos="18" locFile="SimpleSample_Desktop_2012/DirectXTK_Desktop_2012/Src/EffectCommon.h" /><StdViol sev="2" ln="141" cat="OOP" hash="-526459925" tool="c++test" locType="sr" msg="Data members 'mMutex' is declared as 'protected'" lang="cpp" rule="OOP-19" config="1" auth="464642" locStartln="141" locStartPos="19" locEndLn="141" locEndPos="20" locFile="SimpleSample_Desktop_2012/DirectXTK_Desktop_2012/Src/EffectCommon.h" /></ResultInfo></ResultsList>